sphinx_django_theme/__init__.py
sphinx_django_theme-0.0.1.dev0.dist-info/LICENSE
sphinx_django_theme-0.0.1.dev0.dist-info/METADATA
sphinx_django_theme-0.0.1.dev0.dist-info/WHEEL
sphinx_django_theme-0.0.1.dev0.dist-info/top_level.txt
sphinx_django_theme-0.0.1.dev0.dist-info/RECORD
