Metadata-Version: 2.1
Name: sphinx-django-theme
Version: 0.0.1.dev0
Summary: sphinx theme for django projects
Home-page: https://github.com/cizario/sphinx-django-theme/
Author: Nizar DELLELI
Author-email: nizar.delleli@gmail.com
License: BSD 3-Clause
Download-URL: https://github.com/cizario/sphinx-django-theme/
Project-URL: Tracker, https://github.com/cizario/sphinx-django-theme/issues
Project-URL: Source, https://github.com/cizario/sphinx-django-theme/
Project-URL: Release notes, https://github.com/cizario/sphinx-django-theme/releases
Project-URL: Documentation, https://sphinx-django-theme.readthedocs.io/en/latest/
Keywords: sphinx django theme
Platform: UNKNOWN
Classifier: Development Status :: 1 - Planning
Classifier: Environment :: Console
Classifier: Environment :: Web Environment
Classifier: Framework :: Sphinx
Classifier: Framework :: Sphinx :: Theme
Classifier: Intended Audience :: Developers
Classifier: License :: OSI Approved :: BSD License
Classifier: Operating System :: OS Independent
Classifier: Programming Language :: JavaScript
Classifier: Programming Language :: Python
Classifier: Programming Language :: Python :: 3
Classifier: Programming Language :: Python :: 3.6
Classifier: Programming Language :: Python :: 3.7
Classifier: Programming Language :: Python :: 3.8
Classifier: Programming Language :: Python :: 3.9
Classifier: Programming Language :: Python :: 3 :: Only
Classifier: Topic :: Documentation
Classifier: Topic :: Documentation :: Sphinx
Classifier: Topic :: Software Development :: Documentation
Requires-Python: >=3.6
